{
    "Spirituosenschrank": [
        "v5"
    ],
    "Fleischtheke": [
        "vA10"
    ],
    "Sonstiges (Kasse)": [
        "vW1",
        "vW2",
        "vW3"
    ],
    "Obst & Gemüse": [
        "v1",
        "v2",
        "vA2",
        "vB2"
    ],
    "Backwaren": [
        "v3",
        "vA4",
        "vB4"
    ],
    "Fisch & Wurstwaren": [
        "vD6",
        "vC3",
        "vA9_2"
    ],
    "Drogerie & Haushalt": [
        "vA7"
    ],
    "Kühlregal (Molkerei)": [
        "vA9"
    ],
    "Kühlregal (Vegan & Käse)": [
        "vD4"
    ],
    "Tiefkühlware": [
        "vB7"
    ],
    "Trockensortiment & Konserven": [
        "vC5"
    ],
    "Gewürze & Backzutaten": [
        "vD2",
        "vC2"
    ],
    "Getränke Alkoholfrei": [
        "vA6",
        "vB10",
        "vC6"
    ],
    "Bier & Wein": [
        "vD1",
        "vB6"
    ],
    "Kaffee & Tee": [
        "vD5"
    ],
    "Süßwaren & Snacks": [
        "vC7"
    ],
    "Fitness & Sport": [
        "vB9"
    ]
}